cses_aid/__init__.py
cses_aid/helpers.py
cses_aid-0.1.0.dist-info/licenses/LICENSE
cses_aid-0.1.0.dist-info/METADATA
cses_aid-0.1.0.dist-info/WHEEL
cses_aid-0.1.0.dist-info/top_level.txt
cses_aid-0.1.0.dist-info/RECORD
