Metadata-Version: 2.4
Name: cses-aid
Version: 0.1.0
Summary: A collection of helper functions for competitive programming and algorithm problem solving
Author: Shlok Kothari
License-Expression: MIT
Project-URL: Homepage, https://github.com/effaf/cses-aid
Project-URL: Documentation, https://github.com/effaf/cses-aid#readme
Keywords: competitive-programming,algorithms,data-structures,cses
Classifier: Development Status :: 3 - Alpha
Classifier: Intended Audience :: Education
Classifier: Topic :: Education
Classifier: Topic :: Software Development :: Libraries :: Python Modules
Requires-Python: >=3.8
License-File: LICENSE
Dynamic: license-file
